swiftmock/__init__.py
swiftmock/fixtures.py
swiftmock/swift.py
swiftmock-0.0.1.dist-info/LICENSE
swiftmock-0.0.1.dist-info/METADATA
swiftmock-0.0.1.dist-info/WHEEL
swiftmock-0.0.1.dist-info/entry_points.txt
swiftmock-0.0.1.dist-info/top_level.txt
swiftmock-0.0.1.dist-info/zip-safe
swiftmock-0.0.1.dist-info/RECORD
