Metadata-Version: 2.1
Name: swiftmock
Version: 0.0.1
Summary: A mock backend for testing swift.
Home-page: https://github.com/canonical/swiftmock
Author: Dan Ryan
Author-email: dan.ryan@canonical.com
License: Apache-2.0
Project-URL: Source Code, https://github.com/canonical/swiftmock
Project-URL: Change Log, https://github.com/canonical/swiftmock/CHANGES.rst
Keywords: openstack,swift,pytest,mock
Platform: UNKNOWN
Classifier: Development Status :: 4 - Beta
Classifier: License :: OSI Approved :: Apache Software License
Classifier: Framework :: Pytest
Classifier: Operating System :: OS Independent
Classifier: Programming Language :: Python :: 3
Classifier: Programming Language :: Python :: 3.6
Classifier: Programming Language :: Python :: 3.7
Classifier: Programming Language :: Python :: 3.8
Classifier: Topic :: Software Development :: Libraries :: Python Modules
Requires-Python: >=3.6
Requires-Dist: requests
Requires-Dist: python-swiftclient
Requires-Dist: pytest (>=4.4.0)
Provides-Extra: dev
Requires-Dist: invoke ; extra == 'dev'
Requires-Dist: pre-commit ; extra == 'dev'
Requires-Dist: rope ; extra == 'dev'
Provides-Extra: lint
Requires-Dist: black ; extra == 'lint'
Requires-Dist: flake8 ; extra == 'lint'
Requires-Dist: flake8-bugbear ; extra == 'lint'
Requires-Dist: isort ; extra == 'lint'
Requires-Dist: mypy ; extra == 'lint'
Provides-Extra: release
Requires-Dist: parver ; extra == 'release'
Requires-Dist: towncrier ; extra == 'release'
Provides-Extra: tests
Requires-Dist: coverage ; extra == 'tests'
Requires-Dist: pytest-timeout ; extra == 'tests'
Requires-Dist: readme-renderer[md] ; extra == 'tests'
Requires-Dist: twine ; extra == 'tests'
